{
  "generatedAt": "2026-07-15T09:41:47.454431+00:00",
  "installPassed": false,
  "buildPassed": false,
  "installExitCode": 1,
  "buildExitCode": 99,
  "installLogTail": "npm error code EUSAGE\nnpm error\nnpm error `npm ci` can only install packages when your package.json and package-lock.json or npm-shrinkwrap.json are in sync. Please update your lock file with `npm install` before continuing.\nnpm error\nnpm error Invalid: lock file's jspdf@4.0.0 does not satisfy jspdf@4.2.1\nnpm error\nnpm error Clean install a project\nnpm error\nnpm error Usage:\nnpm error npm ci\nnpm error\nnpm error Options:\nnpm error [--install-strategy <hoisted|nested|shallow|linked>] [--legacy-bundling]\nnpm error [--global-style] [--omit <dev|optional|peer> [--omit <dev|optional|peer> ...]]\nnpm error [--include <prod|dev|optional|peer> [--include <prod|dev|optional|peer> ...]]\nnpm error [--strict-peer-deps] [--foreground-scripts] [--ignore-scripts] [--no-audit]\nnpm error [--no-bin-links] [--no-fund] [--dry-run]\nnpm error [-w|--workspace <workspace-name> [-w|--workspace <workspace-name> ...]]\nnpm error [-ws|--workspaces] [--include-workspace-root] [--install-links]\nnpm error\nnpm error aliases: clean-install, ic, install-clean, isntall-clean\nnpm error\nnpm error Run \"npm help ci\" for more info\nnpm error A complete log of this run can be found in: /home/runner/.npm/_logs/2026-07-15T09_41_46_904Z-debug-0.log\n",
  "buildLogTail": ""
}
